[
    {
        "opcode": "loadc",
        "arg": 1050,
        "term": 0
    },
    {
        "opcode": "store",
        "arg": 0,
        "term": 1
    },
    {
        "opcode": "loadc",
        "arg": 1086,
        "term": 2
    },
    {
        "opcode": "store",
        "arg": 1,
        "term": 3
    },
    {
        "opcode": "loadc",
        "arg": 1085,
        "term": 4
    },
    {
        "opcode": "store",
        "arg": 2,
        "term": 5
    },
    {
        "opcode": "loadc",
        "arg": 1077,
        "term": 6
    },
    {
        "opcode": "store",
        "arg": 3,
        "term": 7
    },
    {
        "opcode": "loadc",
        "arg": 1094,
        "term": 8
    },
    {
        "opcode": "store",
        "arg": 4,
        "term": 9
    },
    {
        "opcode": "loadc",
        "arg": 32,
        "term": 10
    },
    {
        "opcode": "store",
        "arg": 5,
        "term": 11
    },
    {
        "opcode": "loadc",
        "arg": 1094,
        "term": 12
    },
    {
        "opcode": "store",
        "arg": 6,
        "term": 13
    },
    {
        "opcode": "loadc",
        "arg": 1080,
        "term": 14
    },
    {
        "opcode": "store",
        "arg": 7,
        "term": 15
    },
    {
        "opcode": "loadc",
        "arg": 1082,
        "term": 16
    },
    {
        "opcode": "store",
        "arg": 8,
        "term": 17
    },
    {
        "opcode": "loadc",
        "arg": 1083,
        "term": 18
    },
    {
        "opcode": "store",
        "arg": 9,
        "term": 19
    },
    {
        "opcode": "loadc",
        "arg": 1072,
        "term": 20
    },
    {
        "opcode": "store",
        "arg": 10,
        "term": 21
    },
    {
        "opcode": "loadc",
        "arg": 0,
        "term": 22
    },
    {
        "opcode": "store",
        "arg": 11,
        "term": 23
    },
    {
        "opcode": "loadc",
        "arg": 0,
        "term": 24
    },
    {
        "opcode": "store",
        "arg": 13,
        "term": 25
    },
    {
        "opcode": "store",
        "arg": 15,
        "term": 26
    },
    {
        "opcode": "loadc",
        "arg": 1,
        "term": 27
    },
    {
        "opcode": "store",
        "arg": 12,
        "term": 28
    },
    {
        "opcode": "store",
        "arg": 14,
        "term": 29
    },
    {
        "opcode": "load",
        "arg": 12,
        "term": 30
    },
    {
        "opcode": "store",
        "arg": 14,
        "term": 31
    },
    {
        "opcode": "load",
        "arg": 13,
        "term": 32
    },
    {
        "opcode": "store",
        "arg": 15,
        "term": 33
    },
    {
        "opcode": "load",
        "arg": 15,
        "term": 34
    },
    {
        "opcode": "store",
        "arg": 16,
        "term": 35
    },
    {
        "opcode": "addc",
        "arg": -2,
        "term": 36
    },
    {
        "opcode": "jl",
        "arg": 39,
        "term": 37
    },
    {
        "opcode": "jmp",
        "arg": 35,
        "term": 38
    },
    {
        "opcode": "load",
        "arg": 16,
        "term": 39
    },
    {
        "opcode": "store",
        "arg": 15,
        "term": 40
    },
    {
        "opcode": "load",
        "arg": 15,
        "term": 41
    },
    {
        "opcode": "addc",
        "arg": -1,
        "term": 42
    },
    {
        "opcode": "je",
        "arg": 46,
        "term": 43
    },
    {
        "opcode": "loadc",
        "arg": 0,
        "term": 44
    },
    {
        "opcode": "jmp",
        "arg": 47,
        "term": 45
    },
    {
        "opcode": "loadc",
        "arg": 1,
        "term": 46
    },
    {
        "opcode": "store",
        "arg": 15,
        "term": 47
    },
    {
        "opcode": "loadc",
        "arg": 2,
        "term": 48
    },
    {
        "opcode": "store",
        "arg": 14,
        "term": 49
    },
    {
        "opcode": "load",
        "arg": 14,
        "term": 50
    },
    {
        "opcode": "addc",
        "arg": -2,
        "term": 51
    },
    {
        "opcode": "jne",
        "arg": 55,
        "term": 52
    },
    {
        "opcode": "load",
        "arg": 15,
        "term": 53
    },
    {
        "opcode": "je",
        "arg": 91,
        "term": 54
    },
    {
        "opcode": "load",
        "arg": 12,
        "term": 55
    },
    {
        "opcode": "store",
        "arg": 14,
        "term": 56
    },
    {
        "opcode": "load",
        "arg": 13,
        "term": 57
    },
    {
        "opcode": "store",
        "arg": 15,
        "term": 58
    },
    {
        "opcode": "load",
        "arg": 15,
        "term": 59
    },
    {
        "opcode": "store",
        "arg": 16,
        "term": 60
    },
    {
        "opcode": "load",
        "arg": 14,
        "term": 61
    },
    {
        "opcode": "je",
        "arg": 76,
        "term": 62
    },
    {
        "opcode": "addc",
        "arg": -1,
        "term": 63
    },
    {
        "opcode": "je",
        "arg": 86,
        "term": 64
    },
    {
        "opcode": "addc",
        "arg": -1,
        "term": 65
    },
    {
        "opcode": "je",
        "arg": 74,
        "term": 66
    },
    {
        "opcode": "load_indir",
        "arg": 16,
        "term": 67
    },
    {
        "opcode": "je",
        "arg": 88,
        "term": 68
    },
    {
        "opcode": "print",
        "arg": "",
        "term": 69
    },
    {
        "opcode": "load",
        "arg": 16,
        "term": 70
    },
    {
        "opcode": "addc",
        "arg": 1,
        "term": 71
    },
    {
        "opcode": "store",
        "arg": 16,
        "term": 72
    },
    {
        "opcode": "jmp",
        "arg": 67,
        "term": 73
    },
    {
        "opcode": "load",
        "arg": 16,
        "term": 74
    },
    {
        "opcode": "jne",
        "arg": 83,
        "term": 75
    },
    {
        "opcode": "loadc",
        "arg": 78,
        "term": 76
    },
    {
        "opcode": "print",
        "arg": "",
        "term": 77
    },
    {
        "opcode": "loadc",
        "arg": 73,
        "term": 78
    },
    {
        "opcode": "print",
        "arg": "",
        "term": 79
    },
    {
        "opcode": "loadc",
        "arg": 76,
        "term": 80
    },
    {
        "opcode": "print",
        "arg": "",
        "term": 81
    },
    {
        "opcode": "jmp",
        "arg": 88,
        "term": 82
    },
    {
        "opcode": "loadc",
        "arg": 116,
        "term": 83
    },
    {
        "opcode": "print",
        "arg": "",
        "term": 84
    },
    {
        "opcode": "jmp",
        "arg": 88,
        "term": 85
    },
    {
        "opcode": "load",
        "arg": 16,
        "term": 86
    },
    {
        "opcode": "print_int",
        "arg": "",
        "term": 87
    },
    {
        "opcode": "loadc",
        "arg": 10,
        "term": 88
    },
    {
        "opcode": "print",
        "arg": "",
        "term": 89
    },
    {
        "opcode": "jmp",
        "arg": 91,
        "term": 90
    },
    {
        "opcode": "load",
        "arg": 12,
        "term": 91
    },
    {
        "opcode": "store",
        "arg": 16,
        "term": 92
    },
    {
        "opcode": "load",
        "arg": 13,
        "term": 93
    },
    {
        "opcode": "store",
        "arg": 17,
        "term": 94
    },
    {
        "opcode": "load",
        "arg": 17,
        "term": 95
    },
    {
        "opcode": "addc",
        "arg": 1,
        "term": 96
    },
    {
        "opcode": "store",
        "arg": 17,
        "term": 97
    },
    {
        "opcode": "load",
        "arg": 16,
        "term": 98
    },
    {
        "opcode": "store",
        "arg": 12,
        "term": 99
    },
    {
        "opcode": "load",
        "arg": 17,
        "term": 100
    },
    {
        "opcode": "store",
        "arg": 13,
        "term": 101
    },
    {
        "opcode": "load",
        "arg": 12,
        "term": 102
    },
    {
        "opcode": "store",
        "arg": 18,
        "term": 103
    },
    {
        "opcode": "load",
        "arg": 13,
        "term": 104
    },
    {
        "opcode": "store",
        "arg": 19,
        "term": 105
    },
    {
        "opcode": "load",
        "arg": 19,
        "term": 106
    },
    {
        "opcode": "addc",
        "arg": -20,
        "term": 107
    },
    {
        "opcode": "jg",
        "arg": 111,
        "term": 108
    },
    {
        "opcode": "loadc",
        "arg": 0,
        "term": 109
    },
    {
        "opcode": "jmp",
        "arg": 112,
        "term": 110
    },
    {
        "opcode": "loadc",
        "arg": 1,
        "term": 111
    },
    {
        "opcode": "store",
        "arg": 19,
        "term": 112
    },
    {
        "opcode": "loadc",
        "arg": 2,
        "term": 113
    },
    {
        "opcode": "store",
        "arg": 18,
        "term": 114
    },
    {
        "opcode": "load",
        "arg": 18,
        "term": 115
    },
    {
        "opcode": "addc",
        "arg": -2,
        "term": 116
    },
    {
        "opcode": "jne",
        "arg": 120,
        "term": 117
    },
    {
        "opcode": "load",
        "arg": 19,
        "term": 118
    },
    {
        "opcode": "je",
        "arg": 126,
        "term": 119
    },
    {
        "opcode": "loadc",
        "arg": 3,
        "term": 120
    },
    {
        "opcode": "store",
        "arg": 18,
        "term": 121
    },
    {
        "opcode": "loadc",
        "arg": 0,
        "term": 122
    },
    {
        "opcode": "store",
        "arg": 19,
        "term": 123
    },
    {
        "opcode": "jmp",
        "arg": 127,
        "term": 124
    },
    {
        "opcode": "jmp",
        "arg": 126,
        "term": 125
    },
    {
        "opcode": "jmp",
        "arg": 30,
        "term": 126
    },
    {
        "opcode": "load",
        "arg": 19,
        "term": 127
    },
    {
        "opcode": "store",
        "arg": 20,
        "term": 128
    },
    {
        "opcode": "load",
        "arg": 18,
        "term": 129
    },
    {
        "opcode": "je",
        "arg": 144,
        "term": 130
    },
    {
        "opcode": "addc",
        "arg": -1,
        "term": 131
    },
    {
        "opcode": "je",
        "arg": 154,
        "term": 132
    },
    {
        "opcode": "addc",
        "arg": -1,
        "term": 133
    },
    {
        "opcode": "je",
        "arg": 142,
        "term": 134
    },
    {
        "opcode": "load_indir",
        "arg": 20,
        "term": 135
    },
    {
        "opcode": "je",
        "arg": 156,
        "term": 136
    },
    {
        "opcode": "print",
        "arg": "",
        "term": 137
    },
    {
        "opcode": "load",
        "arg": 20,
        "term": 138
    },
    {
        "opcode": "addc",
        "arg": 1,
        "term": 139
    },
    {
        "opcode": "store",
        "arg": 20,
        "term": 140
    },
    {
        "opcode": "jmp",
        "arg": 135,
        "term": 141
    },
    {
        "opcode": "load",
        "arg": 20,
        "term": 142
    },
    {
        "opcode": "jne",
        "arg": 151,
        "term": 143
    },
    {
        "opcode": "loadc",
        "arg": 78,
        "term": 144
    },
    {
        "opcode": "print",
        "arg": "",
        "term": 145
    },
    {
        "opcode": "loadc",
        "arg": 73,
        "term": 146
    },
    {
        "opcode": "print",
        "arg": "",
        "term": 147
    },
    {
        "opcode": "loadc",
        "arg": 76,
        "term": 148
    },
    {
        "opcode": "print",
        "arg": "",
        "term": 149
    },
    {
        "opcode": "jmp",
        "arg": 156,
        "term": 150
    },
    {
        "opcode": "loadc",
        "arg": 116,
        "term": 151
    },
    {
        "opcode": "print",
        "arg": "",
        "term": 152
    },
    {
        "opcode": "jmp",
        "arg": 156,
        "term": 153
    },
    {
        "opcode": "load",
        "arg": 20,
        "term": 154
    },
    {
        "opcode": "print_int",
        "arg": "",
        "term": 155
    },
    {
        "opcode": "loadc",
        "arg": 10,
        "term": 156
    },
    {
        "opcode": "print",
        "arg": "",
        "term": 157
    },
    {
        "opcode": "halt",
        "arg": "",
        "term": 158
    }
]